LICENSE.txt
README.md
setup.py
mosaicperm/__init__.py
mosaicperm/core.py
mosaicperm/factor.py
mosaicperm/statistics.py
mosaicperm/tilings.py
mosaicperm/utilities.py
mosaicperm.egg-info/PKG-INFO
mosaicperm.egg-info/SOURCES.txt
mosaicperm.egg-info/dependency_links.txt
mosaicperm.egg-info/requires.txt
mosaicperm.egg-info/top_level.txt
test/__init__.py
test/context.py
test/test_core.py
test/test_factor.py
test/test_tilings.py