Metadata-Version: 2.1
Name: mosaicperm
Version: 0.1.5
Summary: Exact inference via mosaic permutations
Home-page: https://github.com/amspector100/mosaicperm/
Author: Asher Spector
Author-email: amspector100@gmail.com
Classifier: Programming Language :: Python :: 3
Classifier: License :: OSI Approved :: MIT License
Classifier: Operating System :: OS Independent
Requires-Python: >=3.9
License-File: LICENSE.txt
